odoo8_addon_mis_builder-8.0.1.0.2-py2.7-nspkg.pth
odoo8_addon_mis_builder-8.0.1.0.2.dist-info/DESCRIPTION.rst
odoo8_addon_mis_builder-8.0.1.0.2.dist-info/METADATA
odoo8_addon_mis_builder-8.0.1.0.2.dist-info/RECORD
odoo8_addon_mis_builder-8.0.1.0.2.dist-info/WHEEL
odoo8_addon_mis_builder-8.0.1.0.2.dist-info/metadata.json
odoo8_addon_mis_builder-8.0.1.0.2.dist-info/namespace_packages.txt
odoo8_addon_mis_builder-8.0.1.0.2.dist-info/top_level.txt
odoo_addons/mis_builder/CHANGES.rst
odoo_addons/mis_builder/README.rst
odoo_addons/mis_builder/__init__.py
odoo_addons/mis_builder/__openerp__.py
odoo_addons/mis_builder/i18n/de.po
odoo_addons/mis_builder/i18n/es.po
odoo_addons/mis_builder/i18n/es_ES.po
odoo_addons/mis_builder/i18n/fr.po
odoo_addons/mis_builder/i18n/it.po
odoo_addons/mis_builder/i18n/lt.po
odoo_addons/mis_builder/i18n/nl.po
odoo_addons/mis_builder/i18n/sl.po
odoo_addons/mis_builder/migrations/8.0.0.2/pre-migration.py
odoo_addons/mis_builder/models/__init__.py
odoo_addons/mis_builder/models/accounting_none.py
odoo_addons/mis_builder/models/aep.py
odoo_addons/mis_builder/models/aggregate.py
odoo_addons/mis_builder/models/mis_builder.py
odoo_addons/mis_builder/report/__init__.py
odoo_addons/mis_builder/report/mis_builder_xls.py
odoo_addons/mis_builder/report/report_mis_report_instance.py
odoo_addons/mis_builder/report/report_mis_report_instance.xml
odoo_addons/mis_builder/security/ir.model.access.csv
odoo_addons/mis_builder/security/mis_builder_security.xml
odoo_addons/mis_builder/static/description/ex_dashboard.png
odoo_addons/mis_builder/static/description/ex_report.png
odoo_addons/mis_builder/static/description/ex_report_template.png
odoo_addons/mis_builder/static/description/icon.png
odoo_addons/mis_builder/static/description/icon.svg
odoo_addons/mis_builder/static/description/index.html
odoo_addons/mis_builder/static/src/css/custom.css
odoo_addons/mis_builder/static/src/img/icon.png
odoo_addons/mis_builder/static/src/js/mis_builder.js
odoo_addons/mis_builder/static/src/xml/mis_widget.xml
odoo_addons/mis_builder/tests/__init__.py
odoo_addons/mis_builder/tests/mis.report.csv
odoo_addons/mis_builder/tests/mis.report.instance.csv
odoo_addons/mis_builder/tests/mis.report.instance.period.csv
odoo_addons/mis_builder/tests/mis.report.kpi.csv
odoo_addons/mis_builder/tests/mis.report.query.csv
